merlinribeirocalc/__init__.py
merlinribeirocalc/merlinribeirocalc.py
merlinribeirocalc-0.2.dist-info/METADATA
merlinribeirocalc-0.2.dist-info/WHEEL
merlinribeirocalc-0.2.dist-info/top_level.txt
merlinribeirocalc-0.2.dist-info/RECORD
