Metadata-Version: 2.1
Name: merlinribeirocalc
Version: 0.2
Summary: Uma biblioteca de calculadora padrão
Home-page: https://github.com/merlin-ribeiro/
Author: Merlin Ribeiro
Author-email: ribeiro.filho@academico.ifpb.edu.br
License: UNKNOWN
Platform: UNKNOWN
Classifier: Programming Language :: Python :: 3
Classifier: License :: OSI Approved :: MIT License
Classifier: Operating System :: OS Independent
Requires-Python: >=3.6
